{
	"format_version": "1.21.0",
	"minecraft:geometry": [
		{
			"description": {
				"identifier": "geometry.unknown",
				"texture_width": 128,
				"texture_height": 128,
				"visible_bounds_width": 5,
				"visible_bounds_height": 6,
				"visible_bounds_offset": [0, 2, 0]
			},
			"bones": [
				{
					"name": "bb_main",
					"pivot": [0, 0, 0],
					"cubes": [
						{
							"origin": [15.25, 11.25, -22.75],
							"size": [1.5, 1, 1.5],
							"pivot": [16, 11.25, -22],
							"rotation": [0, -45, 0],
							"uv": {
								"north": {"uv": [44, 112], "uv_size": [2, 1]},
								"east": {"uv": [44, 112], "uv_size": [2, 1]},
								"south": {"uv": [44, 112], "uv_size": [2, 1]},
								"west": {"uv": [44, 112], "uv_size": [2, 1]},
								"up": {"uv": [43, 114], "uv_size": [-2, -2]},
								"down": {"uv": [46, 114], "uv_size": [-2, -2]}
							}
						},
						{
							"origin": [-16.75, 11.25, -22.75],
							"size": [1.5, 1, 1.5],
							"pivot": [-16, 11.25, -22],
							"rotation": [0, -45, 0],
							"uv": {
								"north": {"uv": [44, 112], "uv_size": [2, 1]},
								"east": {"uv": [44, 112], "uv_size": [2, 1]},
								"south": {"uv": [44, 112], "uv_size": [2, 1]},
								"west": {"uv": [44, 112], "uv_size": [2, 1]},
								"up": {"uv": [43, 114], "uv_size": [-2, -2]},
								"down": {"uv": [46, 114], "uv_size": [-2, -2]}
							}
						},
						{
							"origin": [-0.75, 10.25, -23.75],
							"size": [1.5, 1, 1.5],
							"pivot": [0, 10.25, -23],
							"rotation": [0, -45, 0],
							"uv": {
								"north": {"uv": [44, 112], "uv_size": [2, 1]},
								"east": {"uv": [44, 112], "uv_size": [2, 1]},
								"south": {"uv": [44, 112], "uv_size": [2, 1]},
								"west": {"uv": [44, 112], "uv_size": [2, 1]},
								"up": {"uv": [43, 117], "uv_size": [-2, -2]},
								"down": {"uv": [46, 114], "uv_size": [-2, -2]}
							}
						},
						{
							"origin": [-0.75, 10.25, 21.75],
							"size": [1.5, 1, 1.5],
							"pivot": [0, 10.25, 22.5],
							"rotation": [0, -45, 0],
							"uv": {
								"north": {"uv": [44, 112], "uv_size": [2, 1]},
								"east": {"uv": [44, 112], "uv_size": [2, 1]},
								"south": {"uv": [44, 112], "uv_size": [2, 1]},
								"west": {"uv": [44, 112], "uv_size": [2, 1]},
								"up": {"uv": [43, 117], "uv_size": [-2, -2]},
								"down": {"uv": [46, 114], "uv_size": [-2, -2]}
							}
						},
						{
							"origin": [15.25, 11.25, 20.75],
							"size": [1.5, 1, 1.5],
							"pivot": [16, 11.25, 21.5],
							"rotation": [0, -45, 0],
							"uv": {
								"north": {"uv": [44, 112], "uv_size": [2, 1]},
								"east": {"uv": [44, 112], "uv_size": [2, 1]},
								"south": {"uv": [44, 112], "uv_size": [2, 1]},
								"west": {"uv": [44, 112], "uv_size": [2, 1]},
								"up": {"uv": [43, 114], "uv_size": [-2, -2]},
								"down": {"uv": [46, 114], "uv_size": [-2, -2]}
							}
						},
						{
							"origin": [-16.75, 11.25, 20.75],
							"size": [1.5, 1, 1.5],
							"pivot": [-16, 11.25, 21.5],
							"rotation": [0, -45, 0],
							"uv": {
								"north": {"uv": [44, 112], "uv_size": [2, 1]},
								"east": {"uv": [44, 112], "uv_size": [2, 1]},
								"south": {"uv": [44, 112], "uv_size": [2, 1]},
								"west": {"uv": [44, 112], "uv_size": [2, 1]},
								"up": {"uv": [43, 114], "uv_size": [-2, -2]},
								"down": {"uv": [46, 114], "uv_size": [-2, -2]}
							}
						}
					]
				},
				{
					"name": "bone",
					"pivot": [0, 0, 0],
					"cubes": [
						{
							"origin": [-6, 36, 8],
							"size": [8, 1, 8],
							"uv": {
								"north": {"uv": [10, 61], "uv_size": [8, 1]},
								"east": {"uv": [18, 61], "uv_size": [8, 1]},
								"south": {"uv": [10, 61], "uv_size": [8, 1]},
								"west": {"uv": [18, 61], "uv_size": [8, 1]},
								"up": {"uv": [10, 77], "uv_size": [-8, -8]},
								"down": {"uv": [10, 77], "uv_size": [-8, -8]}
							}
						},
						{
							"origin": [-5, 37, 9],
							"size": [6, 27, 6],
							"uv": {
								"north": {"uv": [11, 62], "uv_size": [6, 27]},
								"east": {"uv": [19, 62], "uv_size": [6, 27]},
								"south": {"uv": [11, 62], "uv_size": [6, 27]},
								"west": {"uv": [19, 62], "uv_size": [6, 27]},
								"up": {"uv": [9, 68], "uv_size": [-6, -6]},
								"down": {"uv": [9, 68], "uv_size": [-6, -6]}
							}
						},
						{
							"origin": [12, 36, 10],
							"size": [5, 1, 5],
							"uv": {
								"north": {"uv": [25, 112], "uv_size": [5, 1]},
								"east": {"uv": [25, 112], "uv_size": [5, 1]},
								"south": {"uv": [25, 112], "uv_size": [5, 1]},
								"west": {"uv": [25, 112], "uv_size": [5, 1]},
								"up": {"uv": [30, 118], "uv_size": [-5, -5]},
								"down": {"uv": [30, 118], "uv_size": [-5, -5]}
							}
						},
						{
							"origin": [12, 36, 2],
							"size": [5, 1, 5],
							"uv": {
								"north": {"uv": [25, 112], "uv_size": [5, 1]},
								"east": {"uv": [25, 112], "uv_size": [5, 1]},
								"south": {"uv": [25, 112], "uv_size": [5, 1]},
								"west": {"uv": [25, 112], "uv_size": [5, 1]},
								"up": {"uv": [30, 118], "uv_size": [-5, -5]},
								"down": {"uv": [30, 118], "uv_size": [-5, -5]}
							}
						},
						{
							"origin": [-22, 48, -14],
							"size": [12, 2, 12],
							"uv": {
								"north": {"uv": [55, 12], "uv_size": [12, 2]},
								"east": {"uv": [55, 12], "uv_size": [12, 2]},
								"south": {"uv": [55, 12], "uv_size": [12, 2]},
								"west": {"uv": [55, 12], "uv_size": [12, 2]},
								"up": {"uv": [109, 12], "uv_size": [-12, -12]},
								"down": {"uv": [13, 12], "uv_size": [-12, -12]}
							}
						},
						{
							"origin": [-22, 48, 3],
							"size": [12, 2, 12],
							"uv": {
								"north": {"uv": [55, 12], "uv_size": [12, 2]},
								"east": {"uv": [55, 12], "uv_size": [12, 2]},
								"south": {"uv": [55, 12], "uv_size": [12, 2]},
								"west": {"uv": [55, 12], "uv_size": [12, 2]},
								"up": {"uv": [67, 12], "uv_size": [-12, -12]},
								"down": {"uv": [13, 12], "uv_size": [-12, -12]}
							}
						},
						{
							"origin": [-23, 2, -15],
							"size": [14, 46, 14],
							"uv": {
								"north": {"uv": [54, 14], "uv_size": [14, 46]},
								"east": {"uv": [82, 14], "uv_size": [14, 46]},
								"south": {"uv": [54, 14], "uv_size": [14, 46]},
								"west": {"uv": [68, 14], "uv_size": [14, 46]},
								"up": {"uv": [82, 14], "uv_size": [-14, -14]},
								"down": {"uv": [15, 14], "uv_size": [-14, -14]}
							}
						},
						{
							"origin": [-23, 2, 2],
							"size": [14, 46, 14],
							"uv": {
								"north": {"uv": [54, 14], "uv_size": [14, 46]},
								"east": {"uv": [96, 14], "uv_size": [14, 46]},
								"south": {"uv": [54, 14], "uv_size": [14, 46]},
								"west": {"uv": [68, 14], "uv_size": [14, 46]},
								"up": {"uv": [82, 14], "uv_size": [-14, -14]},
								"down": {"uv": [15, 14], "uv_size": [-14, -14]}
							}
						},
						{
							"origin": [-7, 2, -6],
							"size": [27, 24, 26],
							"uv": {
								"north": {"uv": [26, 10], "uv_size": [27, 24]},
								"east": {"uv": [26, 10], "uv_size": [-26, 24]},
								"south": {"uv": [27, 44], "uv_size": [27, 24]},
								"west": {"uv": [0, 10], "uv_size": [26, 24]},
								"up": {"uv": [27, 61], "uv_size": [-27, -26]},
								"down": {"uv": [27, 26], "uv_size": [-27, -26]}
							}
						},
						{
							"origin": [-7, 26, -6],
							"size": [27, 10, 24],
							"uv": {
								"north": {"uv": [26, 0], "uv_size": [27, 10]},
								"east": {"uv": [24, 0], "uv_size": [-24, 10]},
								"south": {"uv": [27, 34], "uv_size": [27, 10]},
								"west": {"uv": [0, 0], "uv_size": [24, 10]},
								"up": {"uv": [27, 59], "uv_size": [-27, -24]},
								"down": {"uv": [27, 24], "uv_size": [-27, -24]}
							}
						},
						{
							"origin": [-7, 2, -21],
							"size": [14, 28, 15],
							"uv": {
								"north": {"uv": [26, 68], "uv_size": [14, 28]},
								"east": {"uv": [40, 68], "uv_size": [15, 28]},
								"south": {"uv": [26, 68], "uv_size": [14, 28]},
								"west": {"uv": [40, 68], "uv_size": [15, 28]},
								"up": {"uv": [54, 111], "uv_size": [-14, -15]},
								"down": {"uv": [54, 111], "uv_size": [-14, -15]}
							}
						},
						{
							"origin": [7, 2, -18],
							"size": [4, 22, 8],
							"uv": {
								"north": {"uv": [55, 74], "uv_size": [4, 22]},
								"east": {"uv": [60, 74], "uv_size": [8, 22]},
								"south": {"uv": [55, 74], "uv_size": [4, 22]},
								"west": {"uv": [60, 74], "uv_size": [8, 22]},
								"up": {"uv": [59, 72], "uv_size": [-4, -8]},
								"down": {"uv": [59, 72], "uv_size": [-4, -8]}
							}
						},
						{
							"origin": [7, 24, -18],
							"size": [3, 2, 8],
							"uv": {
								"north": {"uv": [55, 72], "uv_size": [3, 2]},
								"east": {"uv": [60, 72], "uv_size": [8, 2]},
								"south": {"uv": [55, 72], "uv_size": [3, 2]},
								"west": {"uv": [60, 72], "uv_size": [8, 2]},
								"up": {"uv": [59, 72], "uv_size": [-3, -8]},
								"down": {"uv": [59, 72], "uv_size": [-3, -8]}
							}
						},
						{
							"origin": [20, 4, -4],
							"size": [2, 12, 8],
							"uv": {
								"north": {"uv": [9, 99], "uv_size": [2, 12]},
								"east": {"uv": [0, 99], "uv_size": [8, 12]},
								"south": {"uv": [9, 99], "uv_size": [2, 12]},
								"west": {"uv": [0, 99], "uv_size": [8, 12]},
								"up": {"uv": [11, 107], "uv_size": [-2, -8]},
								"down": {"uv": [11, 107], "uv_size": [-2, -8]}
							}
						},
						{
							"origin": [20, 7, 4],
							"size": [1, 2, 9],
							"uv": {
								"north": {"uv": [10, 102], "uv_size": [1, 2]},
								"east": {"uv": [2, 95], "uv_size": [9, 2]},
								"south": {"uv": [10, 102], "uv_size": [1, 2]},
								"west": {"uv": [2, 95], "uv_size": [9, 2]},
								"up": {"uv": [12, 110], "uv_size": [-1, -9]},
								"down": {"uv": [12, 110], "uv_size": [-1, -9]}
							}
						}
					]
				},
				{
					"name": "inputs",
					"parent": "bone",
					"pivot": [-8, 8, 8],
					"cubes": [
						{
							"origin": [-21, 3, 23],
							"size": [10, 10, 1],
							"uv": {
								"north": {"uv": [0, 118], "uv_size": [10, 10]},
								"east": {"uv": [19, 118], "uv_size": [1, 10]},
								"south": {"uv": [0, 118], "uv_size": [10, 10]},
								"west": {"uv": [19, 118], "uv_size": [1, 10]},
								"up": {"uv": [11, 128], "uv_size": [-1, -10], "uv_rotation": 90},
								"down": {"uv": [11, 128], "uv_size": [-1, -10], "uv_rotation": 270}
							}
						},
						{
							"origin": [11, 3, 23],
							"size": [10, 10, 1],
							"uv": {
								"north": {"uv": [10, 118], "uv_size": [10, 10]},
								"east": {"uv": [19, 118], "uv_size": [1, 10]},
								"south": {"uv": [10, 118], "uv_size": [10, 10]},
								"west": {"uv": [19, 118], "uv_size": [1, 10]},
								"up": {"uv": [11, 128], "uv_size": [-1, -10], "uv_rotation": 90},
								"down": {"uv": [11, 128], "uv_size": [-1, -10], "uv_rotation": 270}
							}
						},
						{
							"origin": [20, 5, 13],
							"size": [3, 6, 6],
							"uv": {
								"north": {"uv": [20, 112], "uv_size": [3, 6]},
								"east": {"uv": [12, 112], "uv_size": [6, 6]},
								"south": {"uv": [20, 112], "uv_size": [3, 6]},
								"west": {"uv": [12, 112], "uv_size": [6, 6]},
								"up": {"uv": [20, 100], "uv_size": [-6, -3], "uv_rotation": 90},
								"down": {"uv": [20, 100], "uv_size": [-6, -3], "uv_rotation": 270}
							}
						},
						{
							"origin": [22, 5, -3],
							"size": [1, 6, 6],
							"uv": {
								"north": {"uv": [20, 112], "uv_size": [3, 6]},
								"east": {"uv": [6, 112], "uv_size": [6, 6]},
								"south": {"uv": [20, 112], "uv_size": [3, 6]},
								"west": {"uv": [6, 112], "uv_size": [6, 6]},
								"up": {"uv": [20, 100], "uv_size": [-6, -3], "uv_rotation": 90},
								"down": {"uv": [20, 100], "uv_size": [-6, -3], "uv_rotation": 270}
							}
						},
						{
							"origin": [-3, 5, 20],
							"size": [6, 6, 4],
							"uv": {
								"north": {"uv": [0, 112], "uv_size": [6, 6]},
								"east": {"uv": [20, 112], "uv_size": [3, 6]},
								"south": {"uv": [0, 112], "uv_size": [6, 6]},
								"west": {"uv": [20, 112], "uv_size": [3, 6]},
								"up": {"uv": [22, 118], "uv_size": [-3, -6], "uv_rotation": 90},
								"down": {"uv": [22, 118], "uv_size": [-3, -6], "uv_rotation": 270}
							}
						},
						{
							"origin": [11, 3, -24],
							"size": [10, 10, 1],
							"uv": {
								"north": {"uv": [10, 118], "uv_size": [10, 10]},
								"east": {"uv": [19, 118], "uv_size": [1, 10]},
								"south": {"uv": [10, 118], "uv_size": [10, 10]},
								"west": {"uv": [19, 118], "uv_size": [1, 10]},
								"up": {"uv": [11, 128], "uv_size": [-1, -10], "uv_rotation": 90},
								"down": {"uv": [11, 128], "uv_size": [-1, -10], "uv_rotation": 270}
							}
						},
						{
							"origin": [-3, 5, -24],
							"size": [6, 6, 3],
							"uv": {
								"north": {"uv": [0, 112], "uv_size": [6, 6]},
								"east": {"uv": [20, 112], "uv_size": [3, 6]},
								"south": {"uv": [0, 112], "uv_size": [6, 6]},
								"west": {"uv": [20, 112], "uv_size": [3, 6]},
								"up": {"uv": [22, 118], "uv_size": [-3, -6], "uv_rotation": 90},
								"down": {"uv": [22, 118], "uv_size": [-3, -6], "uv_rotation": 270}
							}
						},
						{
							"origin": [-21, 3, -24],
							"size": [10, 10, 1],
							"uv": {
								"north": {"uv": [0, 118], "uv_size": [10, 10]},
								"east": {"uv": [19, 118], "uv_size": [1, 10]},
								"south": {"uv": [0, 118], "uv_size": [10, 10]},
								"west": {"uv": [19, 118], "uv_size": [1, 10]},
								"up": {"uv": [11, 128], "uv_size": [-1, -10], "uv_rotation": 90},
								"down": {"uv": [11, 128], "uv_size": [-1, -10], "uv_rotation": 270}
							}
						}
					]
				},
				{
					"name": "base",
					"parent": "bone",
					"pivot": [0, 0, 0],
					"cubes": [
						{
							"origin": [-8, 0, -8],
							"size": [16, 2, 16],
							"uv": {
								"north": {"uv": [112, 126], "uv_size": [16, 2]},
								"east": {"uv": [112, 126], "uv_size": [16, 2]},
								"south": {"uv": [112, 126], "uv_size": [16, 2]},
								"west": {"uv": [112, 126], "uv_size": [16, 2]},
								"up": {"uv": [128, 128], "uv_size": [-16, -16]},
								"down": {"uv": [128, 128], "uv_size": [-16, -16]}
							}
						},
						{
							"origin": [-8, 0, -24],
							"size": [16, 2, 16],
							"uv": {
								"north": {"uv": [112, 126], "uv_size": [16, 2]},
								"east": {"uv": [112, 126], "uv_size": [16, 2]},
								"south": {"uv": [112, 126], "uv_size": [16, 2]},
								"west": {"uv": [112, 126], "uv_size": [16, 2]},
								"up": {"uv": [128, 128], "uv_size": [-16, -16]},
								"down": {"uv": [128, 128], "uv_size": [-16, -16]}
							}
						},
						{
							"origin": [-8, 0, 8],
							"size": [16, 2, 16],
							"uv": {
								"north": {"uv": [112, 126], "uv_size": [16, 2]},
								"east": {"uv": [112, 126], "uv_size": [16, 2]},
								"south": {"uv": [112, 126], "uv_size": [16, 2]},
								"west": {"uv": [112, 126], "uv_size": [16, 2]},
								"up": {"uv": [128, 128], "uv_size": [-16, -16]},
								"down": {"uv": [128, 128], "uv_size": [-16, -16]}
							}
						},
						{
							"origin": [-24, 0, 8],
							"size": [16, 2, 16],
							"uv": {
								"north": {"uv": [112, 126], "uv_size": [16, 2]},
								"east": {"uv": [112, 126], "uv_size": [16, 2]},
								"south": {"uv": [112, 126], "uv_size": [16, 2]},
								"west": {"uv": [112, 126], "uv_size": [16, 2]},
								"up": {"uv": [128, 128], "uv_size": [-16, -16]},
								"down": {"uv": [128, 128], "uv_size": [-16, -16]}
							}
						},
						{
							"origin": [-24, 0, -24],
							"size": [16, 2, 16],
							"uv": {
								"north": {"uv": [112, 126], "uv_size": [16, 2]},
								"east": {"uv": [112, 126], "uv_size": [16, 2]},
								"south": {"uv": [112, 126], "uv_size": [16, 2]},
								"west": {"uv": [112, 126], "uv_size": [16, 2]},
								"up": {"uv": [128, 128], "uv_size": [-16, -16]},
								"down": {"uv": [128, 128], "uv_size": [-16, -16]}
							}
						},
						{
							"origin": [-24, 0, -8],
							"size": [16, 2, 16],
							"uv": {
								"north": {"uv": [112, 126], "uv_size": [16, 2]},
								"east": {"uv": [112, 126], "uv_size": [16, 2]},
								"south": {"uv": [112, 126], "uv_size": [16, 2]},
								"west": {"uv": [112, 126], "uv_size": [16, 2]},
								"up": {"uv": [128, 128], "uv_size": [-16, -16]},
								"down": {"uv": [128, 128], "uv_size": [-16, -16]}
							}
						},
						{
							"origin": [8, 0, -8],
							"size": [16, 2, 16],
							"uv": {
								"north": {"uv": [112, 126], "uv_size": [16, 2]},
								"east": {"uv": [112, 126], "uv_size": [16, 2]},
								"south": {"uv": [112, 126], "uv_size": [16, 2]},
								"west": {"uv": [112, 126], "uv_size": [16, 2]},
								"up": {"uv": [128, 128], "uv_size": [-16, -16]},
								"down": {"uv": [128, 128], "uv_size": [-16, -16]}
							}
						},
						{
							"origin": [8, 0, 8],
							"size": [16, 2, 16],
							"uv": {
								"north": {"uv": [112, 126], "uv_size": [16, 2]},
								"east": {"uv": [112, 126], "uv_size": [16, 2]},
								"south": {"uv": [112, 126], "uv_size": [16, 2]},
								"west": {"uv": [112, 126], "uv_size": [16, 2]},
								"up": {"uv": [128, 128], "uv_size": [-16, -16]},
								"down": {"uv": [128, 128], "uv_size": [-16, -16]}
							}
						},
						{
							"origin": [8, 0, -24],
							"size": [16, 2, 16],
							"uv": {
								"north": {"uv": [112, 126], "uv_size": [16, 2]},
								"east": {"uv": [112, 126], "uv_size": [16, 2]},
								"south": {"uv": [112, 126], "uv_size": [16, 2]},
								"west": {"uv": [112, 126], "uv_size": [16, 2]},
								"up": {"uv": [128, 128], "uv_size": [-16, -16]},
								"down": {"uv": [128, 128], "uv_size": [-16, -16]}
							}
						}
					]
				},
				{
					"name": "blankpipes",
					"parent": "bone",
					"pivot": [0, 0, 0],
					"cubes": [
						{
							"origin": [-5, 36, 5],
							"size": [1, 3, 1],
							"uv": {
								"north": {"uv": [113, 35], "uv_size": [1, 3]},
								"east": {"uv": [113, 35], "uv_size": [1, 3]},
								"south": {"uv": [113, 35], "uv_size": [1, 3]},
								"west": {"uv": [113, 35], "uv_size": [1, 3]},
								"up": {"uv": [117, 27], "uv_size": [-1, -1]},
								"down": {"uv": [117, 27], "uv_size": [-1, -1]}
							}
						},
						{
							"origin": [-5, 36, 3],
							"size": [1, 3, 1],
							"uv": {
								"north": {"uv": [112, 45], "uv_size": [1, 3]},
								"east": {"uv": [112, 45], "uv_size": [1, 3]},
								"south": {"uv": [112, 45], "uv_size": [1, 3]},
								"west": {"uv": [112, 45], "uv_size": [1, 3]},
								"up": {"uv": [117, 27], "uv_size": [-1, -1]},
								"down": {"uv": [117, 27], "uv_size": [-1, -1]}
							}
						},
						{
							"origin": [-5, 36, -4],
							"size": [1, 3, 1],
							"uv": {
								"north": {"uv": [115, 38], "uv_size": [1, 3]},
								"east": {"uv": [115, 38], "uv_size": [1, 3]},
								"south": {"uv": [115, 38], "uv_size": [1, 3]},
								"west": {"uv": [115, 38], "uv_size": [1, 3]},
								"up": {"uv": [117, 27], "uv_size": [-1, -1]},
								"down": {"uv": [117, 27], "uv_size": [-1, -1]}
							}
						},
						{
							"origin": [-25, 6, 7],
							"size": [1, 40, 1],
							"uv": {
								"north": {"uv": [116, 20], "uv_size": [1, 40]},
								"east": {"uv": [116, 20], "uv_size": [1, 40]},
								"south": {"uv": [116, 20], "uv_size": [1, 40]},
								"west": {"uv": [116, 20], "uv_size": [1, 40]},
								"up": {"uv": [117, 21], "uv_size": [-1, -1]},
								"down": {"uv": [117, 21], "uv_size": [-1, -1]}
							}
						},
						{
							"origin": [-18, 12, 17],
							"size": [1, 31, 1],
							"uv": {
								"north": {"uv": [116, 20], "uv_size": [1, 31]},
								"east": {"uv": [116, 20], "uv_size": [1, 31]},
								"south": {"uv": [116, 20], "uv_size": [1, 31]},
								"west": {"uv": [116, 20], "uv_size": [1, 31]},
								"up": {"uv": [117, 21], "uv_size": [-1, -1]},
								"down": {"uv": [117, 21], "uv_size": [-1, -1]}
							}
						},
						{
							"origin": [-25, 6, 4],
							"size": [1, 40, 1],
							"uv": {
								"north": {"uv": [114, 20], "uv_size": [1, 40]},
								"east": {"uv": [114, 20], "uv_size": [1, 40]},
								"south": {"uv": [114, 20], "uv_size": [1, 40]},
								"west": {"uv": [114, 20], "uv_size": [1, 40]},
								"up": {"uv": [115, 21], "uv_size": [-1, -1]},
								"down": {"uv": [115, 21], "uv_size": [-1, -1]}
							}
						},
						{
							"origin": [-25, 14, 9],
							"size": [1, 32, 1],
							"uv": {
								"north": {"uv": [112, 21], "uv_size": [1, 32]},
								"east": {"uv": [112, 21], "uv_size": [1, 32]},
								"south": {"uv": [112, 21], "uv_size": [1, 32]},
								"west": {"uv": [112, 21], "uv_size": [1, 32]},
								"up": {"uv": [113, 22], "uv_size": [-1, -1]},
								"down": {"uv": [113, 22], "uv_size": [-1, -1]}
							}
						},
						{
							"origin": [20, 16, 2],
							"size": [1, 12, 1],
							"uv": {
								"north": {"uv": [39, 102], "uv_size": [1, 12]},
								"east": {"uv": [39, 102], "uv_size": [1, 12]},
								"south": {"uv": [39, 102], "uv_size": [1, 12]},
								"west": {"uv": [39, 102], "uv_size": [1, 12]},
								"up": {"uv": [18, 109], "uv_size": [-1, -1]},
								"down": {"uv": [18, 109], "uv_size": [-1, -1]}
							}
						},
						{
							"origin": [20, 16, 0],
							"size": [1, 14, 1],
							"uv": {
								"north": {"uv": [32, 103], "uv_size": [1, 14]},
								"east": {"uv": [32, 103], "uv_size": [1, 14]},
								"south": {"uv": [32, 103], "uv_size": [1, 14]},
								"west": {"uv": [32, 103], "uv_size": [1, 14]},
								"up": {"uv": [30, 102], "uv_size": [-1, -1]},
								"down": {"uv": [30, 102], "uv_size": [-1, -1]}
							}
						},
						{
							"origin": [-24, 45, 4],
							"size": [1, 1, 1],
							"uv": {
								"north": {"uv": [114, 38], "uv_size": [1, 1]},
								"east": {"uv": [114, 38], "uv_size": [1, 1]},
								"south": {"uv": [114, 38], "uv_size": [1, 1]},
								"west": {"uv": [114, 38], "uv_size": [1, 1]},
								"up": {"uv": [115, 39], "uv_size": [-1, -1]},
								"down": {"uv": [115, 39], "uv_size": [-1, -1]}
							}
						},
						{
							"origin": [-18, 42, 16],
							"size": [1, 1, 1],
							"uv": {
								"north": {"uv": [114, 38], "uv_size": [1, 1]},
								"east": {"uv": [114, 38], "uv_size": [1, 1]},
								"south": {"uv": [114, 38], "uv_size": [1, 1]},
								"west": {"uv": [114, 38], "uv_size": [1, 1]},
								"up": {"uv": [115, 39], "uv_size": [-1, -1]},
								"down": {"uv": [115, 39], "uv_size": [-1, -1]}
							}
						},
						{
							"origin": [-24, 45, 7],
							"size": [1, 1, 1],
							"uv": {
								"north": {"uv": [112, 49], "uv_size": [1, 1]},
								"east": {"uv": [112, 49], "uv_size": [1, 1]},
								"south": {"uv": [112, 49], "uv_size": [1, 1]},
								"west": {"uv": [112, 49], "uv_size": [1, 1]},
								"up": {"uv": [113, 50], "uv_size": [-1, -1]},
								"down": {"uv": [113, 50], "uv_size": [-1, -1]}
							}
						},
						{
							"origin": [-24, 45, 9],
							"size": [1, 1, 1],
							"uv": {
								"north": {"uv": [115, 55], "uv_size": [1, 1]},
								"east": {"uv": [115, 55], "uv_size": [1, 1]},
								"south": {"uv": [115, 55], "uv_size": [1, 1]},
								"west": {"uv": [115, 55], "uv_size": [1, 1]},
								"up": {"uv": [116, 56], "uv_size": [-1, -1]},
								"down": {"uv": [116, 56], "uv_size": [-1, -1]}
							}
						},
						{
							"origin": [-24, 14, 9],
							"size": [1, 1, 1],
							"uv": {
								"north": {"uv": [120, 56], "uv_size": [1, 1]},
								"east": {"uv": [120, 56], "uv_size": [1, 1]},
								"south": {"uv": [120, 56], "uv_size": [1, 1]},
								"west": {"uv": [120, 56], "uv_size": [1, 1]},
								"up": {"uv": [121, 57], "uv_size": [-1, -1]},
								"down": {"uv": [121, 57], "uv_size": [-1, -1]}
							}
						},
						{
							"origin": [-24, 6, 7],
							"size": [1, 1, 1],
							"uv": {
								"north": {"uv": [112, 21], "uv_size": [1, 1]},
								"east": {"uv": [112, 21], "uv_size": [1, 1]},
								"south": {"uv": [112, 21], "uv_size": [1, 1]},
								"west": {"uv": [112, 21], "uv_size": [1, 1]},
								"up": {"uv": [113, 22], "uv_size": [-1, -1]},
								"down": {"uv": [113, 22], "uv_size": [-1, -1]}
							}
						},
						{
							"origin": [-24, 6, 4],
							"size": [1, 1, 1],
							"uv": {
								"north": {"uv": [114, 44], "uv_size": [1, 1]},
								"east": {"uv": [114, 44], "uv_size": [1, 1]},
								"south": {"uv": [114, 44], "uv_size": [1, 1]},
								"west": {"uv": [114, 44], "uv_size": [1, 1]},
								"up": {"uv": [115, 45], "uv_size": [-1, -1]},
								"down": {"uv": [115, 45], "uv_size": [-1, -1]}
							}
						},
						{
							"origin": [-13, 50, -5],
							"size": [1, 2, 1],
							"uv": {
								"north": {"uv": [114, 32], "uv_size": [1, 2]},
								"east": {"uv": [114, 32], "uv_size": [1, 2]},
								"south": {"uv": [114, 32], "uv_size": [1, 2]},
								"west": {"uv": [114, 32], "uv_size": [1, 2]},
								"up": {"uv": [115, 33], "uv_size": [-1, -1]},
								"down": {"uv": [115, 33], "uv_size": [-1, -1]}
							}
						},
						{
							"origin": [-13, 50, 4],
							"size": [1, 2, 1],
							"uv": {
								"north": {"uv": [111, 33], "uv_size": [1, 2]},
								"east": {"uv": [111, 33], "uv_size": [1, 2]},
								"south": {"uv": [111, 33], "uv_size": [1, 2]},
								"west": {"uv": [111, 33], "uv_size": [1, 2]},
								"up": {"uv": [112, 34], "uv_size": [-1, -1]},
								"down": {"uv": [112, 34], "uv_size": [-1, -1]}
							}
						},
						{
							"origin": [-13, 52, -5],
							"size": [1, 1, 10],
							"uv": {
								"north": {"uv": [112, 59], "uv_size": [1, 1]},
								"east": {"uv": [112, 59], "uv_size": [10, 1]},
								"south": {"uv": [112, 59], "uv_size": [1, 1]},
								"west": {"uv": [112, 59], "uv_size": [10, 1]},
								"up": {"uv": [116, 40], "uv_size": [-1, -10]},
								"down": {"uv": [116, 40], "uv_size": [-1, -10]}
							}
						},
						{
							"origin": [-15, 52, -7],
							"size": [1, 1, 12],
							"uv": {
								"north": {"uv": [111, 57], "uv_size": [1, 1]},
								"east": {"uv": [111, 57], "uv_size": [12, 1]},
								"south": {"uv": [111, 57], "uv_size": [1, 1]},
								"west": {"uv": [111, 57], "uv_size": [12, 1]},
								"up": {"uv": [118, 55], "uv_size": [-1, -12]},
								"down": {"uv": [118, 55], "uv_size": [-1, -12]}
							}
						},
						{
							"origin": [-15, 50, -7],
							"size": [1, 2, 1],
							"uv": {
								"north": {"uv": [112, 21], "uv_size": [1, 2]},
								"east": {"uv": [112, 21], "uv_size": [1, 2]},
								"south": {"uv": [112, 21], "uv_size": [1, 2]},
								"west": {"uv": [112, 21], "uv_size": [1, 2]},
								"up": {"uv": [113, 22], "uv_size": [-1, -1]},
								"down": {"uv": [113, 22], "uv_size": [-1, -1]}
							}
						},
						{
							"origin": [-15, 50, 4],
							"size": [1, 2, 1],
							"uv": {
								"north": {"uv": [115, 33], "uv_size": [1, 2]},
								"east": {"uv": [115, 33], "uv_size": [1, 2]},
								"south": {"uv": [115, 33], "uv_size": [1, 2]},
								"west": {"uv": [115, 33], "uv_size": [1, 2]},
								"up": {"uv": [116, 34], "uv_size": [-1, -1]},
								"down": {"uv": [116, 34], "uv_size": [-1, -1]}
							}
						}
					]
				},
				{
					"name": "specialpipes",
					"parent": "bone",
					"pivot": [0, 0, 0],
					"cubes": [
						{
							"origin": [-19, 38, -1],
							"size": [6, 6, 3],
							"uv": {
								"north": {"uv": [56, 97], "uv_size": [6, 6]},
								"east": {"uv": [89, 61], "uv_size": [3, 6]},
								"south": {"uv": [56, 97], "uv_size": [6, 6]},
								"west": {"uv": [90, 61], "uv_size": [3, 6]},
								"up": {"uv": [75, 66], "uv_size": [-6, -3]},
								"down": {"uv": [75, 73], "uv_size": [-6, -3]}
							}
						},
						{
							"origin": [-19, 30, -1],
							"size": [6, 6, 3],
							"uv": {
								"north": {"uv": [56, 97], "uv_size": [6, 6]},
								"east": {"uv": [89, 61], "uv_size": [3, 6]},
								"south": {"uv": [56, 97], "uv_size": [6, 6]},
								"west": {"uv": [90, 61], "uv_size": [3, 6]},
								"up": {"uv": [75, 66], "uv_size": [-6, -3]},
								"down": {"uv": [75, 73], "uv_size": [-6, -3]}
							}
						},
						{
							"origin": [-20, 4, -23],
							"size": [8, 8, 8],
							"uv": {
								"north": {"uv": [19, 101], "uv_size": [8, 8]},
								"east": {"uv": [19, 101], "uv_size": [8, 8]},
								"south": {"uv": [19, 101], "uv_size": [8, 8]},
								"west": {"uv": [19, 101], "uv_size": [8, 8]},
								"up": {"uv": [40, 109], "uv_size": [-8, -8]},
								"down": {"uv": [40, 109], "uv_size": [-8, -8]}
							}
						},
						{
							"origin": [12, 4, -23],
							"size": [8, 8, 17],
							"uv": {
								"north": {"uv": [19, 101], "uv_size": [8, 8]},
								"east": {"uv": [14, 101], "uv_size": [17, 8]},
								"south": {"uv": [32, 105], "uv_size": [8, 8]},
								"west": {"uv": [14, 101], "uv_size": [17, 8]},
								"up": {"uv": [40, 118], "uv_size": [-8, -17]},
								"down": {"uv": [40, 118], "uv_size": [-8, -17]}
							}
						},
						{
							"origin": [12, 4, 20],
							"size": [8, 8, 3],
							"uv": {
								"north": {"uv": [14, 101], "uv_size": [8, 8]},
								"east": {"uv": [14, 101], "uv_size": [3, 8]},
								"south": {"uv": [14, 101], "uv_size": [8, 8]},
								"west": {"uv": [14, 101], "uv_size": [3, 8]},
								"up": {"uv": [40, 110], "uv_size": [-8, -3]},
								"down": {"uv": [40, 110], "uv_size": [-8, -3]}
							}
						},
						{
							"origin": [-20, 4, 16],
							"size": [8, 8, 7],
							"uv": {
								"north": {"uv": [14, 101], "uv_size": [8, 8]},
								"east": {"uv": [14, 101], "uv_size": [7, 8]},
								"south": {"uv": [14, 101], "uv_size": [8, 8]},
								"west": {"uv": [14, 101], "uv_size": [7, 8]},
								"up": {"uv": [40, 113], "uv_size": [-8, -7]},
								"down": {"uv": [40, 113], "uv_size": [-8, -7]}
							}
						},
						{
							"origin": [-12, 5, -21],
							"size": [5, 6, 6],
							"uv": {
								"north": {"uv": [93, 61], "uv_size": [-5, 6]},
								"east": {"uv": [56, 97], "uv_size": [6, 6]},
								"south": {"uv": [88, 67], "uv_size": [5, -6]},
								"west": {"uv": [56, 97], "uv_size": [6, 6]},
								"up": {"uv": [93, 67], "uv_size": [-5, -6]},
								"down": {"uv": [93, 67], "uv_size": [-5, -6]}
							}
						},
						{
							"origin": [11, 5, -17],
							"size": [1, 6, 6],
							"uv": {
								"north": {"uv": [88, 61], "uv_size": [1, 6]},
								"east": {"uv": [88, 61], "uv_size": [6, 6]},
								"south": {"uv": [88, 61], "uv_size": [1, 6]},
								"west": {"uv": [88, 61], "uv_size": [6, 6]},
								"up": {"uv": [89, 67], "uv_size": [-1, -6]},
								"down": {"uv": [89, 67], "uv_size": [-1, -6]}
							}
						},
						{
							"origin": [16, 12, -11],
							"size": [3, 16, 3],
							"uv": {
								"north": {"uv": [76, 79], "uv_size": [3, 16]},
								"east": {"uv": [76, 79], "uv_size": [3, 16]},
								"south": {"uv": [76, 79], "uv_size": [3, 16]},
								"west": {"uv": [76, 79], "uv_size": [3, 16]},
								"up": {"uv": [79, 82], "uv_size": [-3, -3]},
								"down": {"uv": [79, 82], "uv_size": [-3, -3]}
							}
						},
						{
							"origin": [16, 28, -11],
							"size": [3, 3, 5],
							"uv": {
								"north": {"uv": [76, 61], "uv_size": [3, 3]},
								"east": {"uv": [93, 71], "uv_size": [-5, -3]},
								"south": {"uv": [76, 63], "uv_size": [3, 3]},
								"west": {"uv": [122, 61], "uv_size": [-5, 3]},
								"up": {"uv": [79, 68], "uv_size": [-3, -5]},
								"down": {"uv": [79, 68], "uv_size": [-3, -5]}
							}
						},
						{
							"origin": [13, 12, -10],
							"size": [2, 25, 2],
							"uv": {
								"north": {"uv": [80, 63], "uv_size": [2, 25]},
								"east": {"uv": [80, 63], "uv_size": [2, 25]},
								"south": {"uv": [80, 63], "uv_size": [2, 25]},
								"west": {"uv": [80, 63], "uv_size": [2, 25]},
								"up": {"uv": [69, 99], "uv_size": [-2, -2]},
								"down": {"uv": [69, 99], "uv_size": [-2, -2]}
							}
						},
						{
							"origin": [8, 6, 20],
							"size": [2, 24, 2],
							"uv": {
								"north": {"uv": [80, 63], "uv_size": [2, 24]},
								"east": {"uv": [80, 63], "uv_size": [2, 24]},
								"south": {"uv": [80, 63], "uv_size": [2, 24]},
								"west": {"uv": [80, 63], "uv_size": [2, 24]},
								"up": {"uv": [69, 99], "uv_size": [-2, -2]},
								"down": {"uv": [69, 99], "uv_size": [-2, -2]}
							}
						},
						{
							"origin": [-15, 12, -19],
							"size": [2, 34, 2],
							"uv": {
								"north": {"uv": [80, 61], "uv_size": [2, 34]},
								"east": {"uv": [80, 61], "uv_size": [2, 34]},
								"south": {"uv": [80, 61], "uv_size": [2, 34]},
								"west": {"uv": [80, 61], "uv_size": [2, 34]},
								"up": {"uv": [82, 66], "uv_size": [-2, -2]},
								"down": {"uv": [82, 66], "uv_size": [-2, -2]}
							}
						},
						{
							"origin": [-19, 12, -19],
							"size": [2, 27, 2],
							"uv": {
								"north": {"uv": [80, 61], "uv_size": [2, 27]},
								"east": {"uv": [80, 61], "uv_size": [2, 27]},
								"south": {"uv": [80, 61], "uv_size": [2, 27]},
								"west": {"uv": [80, 61], "uv_size": [2, 27]},
								"up": {"uv": [82, 65], "uv_size": [-2, -2]},
								"down": {"uv": [82, 65], "uv_size": [-2, -2]}
							}
						},
						{
							"origin": [-16, 12, 17],
							"size": [2, 19, 2],
							"uv": {
								"north": {"uv": [80, 61], "uv_size": [2, 19]},
								"east": {"uv": [80, 61], "uv_size": [2, 19]},
								"south": {"uv": [80, 61], "uv_size": [2, 19]},
								"west": {"uv": [80, 61], "uv_size": [2, 19]},
								"up": {"uv": [82, 65], "uv_size": [-2, -2]},
								"down": {"uv": [82, 65], "uv_size": [-2, -2]}
							}
						},
						{
							"origin": [-19, 37, -17],
							"size": [2, 2, 2],
							"uv": {
								"north": {"uv": [80, 69], "uv_size": [2, 2]},
								"east": {"uv": [92, 72], "uv_size": [2, 2]},
								"south": {"uv": [80, 69], "uv_size": [2, 2]},
								"west": {"uv": [92, 72], "uv_size": [2, 2]},
								"up": {"uv": [82, 71], "uv_size": [-2, -2]},
								"down": {"uv": [82, 71], "uv_size": [-2, -2]}
							}
						},
						{
							"origin": [-15, 46, -19],
							"size": [2, 2, 4],
							"uv": {
								"north": {"uv": [90, 72], "uv_size": [2, 2]},
								"east": {"uv": [90, 72], "uv_size": [4, 2]},
								"south": {"uv": [89, 72], "uv_size": [2, 2]},
								"west": {"uv": [89, 72], "uv_size": [4, 2]},
								"up": {"uv": [82, 69], "uv_size": [-2, -4]},
								"down": {"uv": [82, 69], "uv_size": [-2, -4]}
							}
						},
						{
							"origin": [-16, 31, 16],
							"size": [2, 2, 3],
							"uv": {
								"north": {"uv": [90, 72], "uv_size": [2, 2]},
								"east": {"uv": [90, 72], "uv_size": [3, 2]},
								"south": {"uv": [89, 72], "uv_size": [2, 2]},
								"west": {"uv": [89, 72], "uv_size": [3, 2]},
								"up": {"uv": [82, 68], "uv_size": [-2, -3]},
								"down": {"uv": [82, 68], "uv_size": [-2, -3]}
							}
						},
						{
							"origin": [13, 36, -4],
							"size": [2, 1, 2],
							"uv": {
								"north": {"uv": [67, 97], "uv_size": [2, 1]},
								"east": {"uv": [67, 97], "uv_size": [2, 1]},
								"south": {"uv": [67, 97], "uv_size": [2, 1]},
								"west": {"uv": [67, 97], "uv_size": [2, 1]},
								"up": {"uv": [69, 99], "uv_size": [-2, -2]},
								"down": {"uv": [69, 99], "uv_size": [-2, -2]}
							}
						},
						{
							"origin": [13, 37, -10],
							"size": [2, 2, 8],
							"uv": {
								"north": {"uv": [67, 97], "uv_size": [2, 2]},
								"east": {"uv": [90, 72], "uv_size": [8, 2]},
								"south": {"uv": [67, 97], "uv_size": [2, 2]},
								"west": {"uv": [90, 72], "uv_size": [8, 2]},
								"up": {"uv": [82, 90], "uv_size": [-2, -8]},
								"down": {"uv": [82, 90], "uv_size": [-2, -8]}
							}
						},
						{
							"origin": [8, 30, 18],
							"size": [2, 2, 4],
							"uv": {
								"north": {"uv": [67, 97], "uv_size": [2, 2]},
								"east": {"uv": [91, 72], "uv_size": [4, 2]},
								"south": {"uv": [67, 97], "uv_size": [2, 2]},
								"west": {"uv": [91, 72], "uv_size": [4, 2]},
								"up": {"uv": [82, 67], "uv_size": [-2, -4]},
								"down": {"uv": [82, 67], "uv_size": [-2, -4]}
							}
						},
						{
							"origin": [12, 12, 20],
							"size": [2, 20, 2],
							"uv": {
								"north": {"uv": [80, 63], "uv_size": [2, 20]},
								"east": {"uv": [80, 63], "uv_size": [2, 20]},
								"south": {"uv": [80, 63], "uv_size": [2, 20]},
								"west": {"uv": [80, 63], "uv_size": [2, 20]},
								"up": {"uv": [69, 99], "uv_size": [-2, -2]},
								"down": {"uv": [69, 99], "uv_size": [-2, -2]}
							}
						},
						{
							"origin": [12, 32, 18],
							"size": [2, 2, 4],
							"uv": {
								"north": {"uv": [67, 97], "uv_size": [2, 2]},
								"east": {"uv": [91, 72], "uv_size": [4, 2]},
								"south": {"uv": [67, 97], "uv_size": [2, 2]},
								"west": {"uv": [91, 72], "uv_size": [4, 2]},
								"up": {"uv": [82, 67], "uv_size": [-2, -4]},
								"down": {"uv": [82, 67], "uv_size": [-2, -4]}
							}
						},
						{
							"origin": [-7, 39, -9],
							"size": [4, 4, 16],
							"uv": {
								"north": {"uv": [70, 67], "uv_size": [4, 4]},
								"east": {"uv": [102, 75], "uv_size": [16, 4]},
								"south": {"uv": [88, 75], "uv_size": [4, 4]},
								"west": {"uv": [106, 75], "uv_size": [16, 4]},
								"up": {"uv": [96, 100], "uv_size": [-4, -16]},
								"down": {"uv": [96, 84], "uv_size": [-4, 16]}
							}
						},
						{
							"origin": [-7, 39, -13],
							"size": [8, 4, 4],
							"uv": {
								"north": {"uv": [114, 80], "uv_size": [8, 4]},
								"east": {"uv": [118, 75], "uv_size": [4, 4]},
								"south": {"uv": [88, 75], "uv_size": [8, 4]},
								"west": {"uv": [70, 97], "uv_size": [4, 4]},
								"up": {"uv": [96, 84], "uv_size": [-8, -4]},
								"down": {"uv": [96, 80], "uv_size": [-8, 4]}
							}
						},
						{
							"origin": [-9, 39, 3],
							"size": [2, 4, 4],
							"uv": {
								"north": {"uv": [88, 75], "uv_size": [2, 4]},
								"east": {"uv": [70, 67], "uv_size": [4, 4]},
								"south": {"uv": [120, 75], "uv_size": [2, 4]},
								"west": {"uv": [70, 67], "uv_size": [4, 4]},
								"up": {"uv": [98, 100], "uv_size": [-2, -4]},
								"down": {"uv": [98, 96], "uv_size": [-2, 4]}
							}
						},
						{
							"origin": [-9, 39, -6],
							"size": [2, 4, 4],
							"uv": {
								"north": {"uv": [70, 67], "uv_size": [2, 4]},
								"east": {"uv": [70, 67], "uv_size": [4, 4]},
								"south": {"uv": [70, 67], "uv_size": [2, 4]},
								"west": {"uv": [70, 67], "uv_size": [4, 4]},
								"up": {"uv": [98, 91], "uv_size": [-2, -4]},
								"down": {"uv": [98, 87], "uv_size": [-2, 4]}
							}
						},
						{
							"origin": [-2, 30, -12],
							"size": [2, 9, 2],
							"uv": {
								"north": {"uv": [80, 63], "uv_size": [2, 9]},
								"east": {"uv": [80, 63], "uv_size": [2, 9]},
								"south": {"uv": [80, 63], "uv_size": [2, 9]},
								"west": {"uv": [80, 63], "uv_size": [2, 9]},
								"up": {"uv": [69, 99], "uv_size": [-2, -2]},
								"down": {"uv": [69, 99], "uv_size": [-2, -2]}
							}
						},
						{
							"origin": [-5, 30, -12],
							"size": [2, 9, 2],
							"uv": {
								"north": {"uv": [80, 63], "uv_size": [2, 9]},
								"east": {"uv": [80, 63], "uv_size": [2, 9]},
								"south": {"uv": [80, 63], "uv_size": [2, 9]},
								"west": {"uv": [80, 63], "uv_size": [2, 9]},
								"up": {"uv": [69, 99], "uv_size": [-2, -2]},
								"down": {"uv": [69, 99], "uv_size": [-2, -2]}
							}
						},
						{
							"origin": [-9, 26, 7],
							"size": [2, 8, 8],
							"uv": {
								"north": {"uv": [14, 101], "uv_size": [2, 8]},
								"east": {"uv": [32, 106], "uv_size": [8, 8]},
								"south": {"uv": [14, 101], "uv_size": [2, 8]},
								"west": {"uv": [32, 106], "uv_size": [8, 8]},
								"up": {"uv": [18, 109], "uv_size": [-2, -8]},
								"down": {"uv": [18, 109], "uv_size": [-2, -8]}
							}
						}
					]
				}
			]
		}
	]
}